{
  "hw-type-1": "Read a passage and answer comprehension questions",
  "hw-type-2": "Read and choose the best title/main idea",
  "hw-type-3": "Read and answer True/False questions",
  "hw-type-4": "Read and complete a summary",
  "hw-type-5": "Read and match headings to paragraphs",
  "hw-type-6": "Read and identify vocabulary from context",
  "hw-type-7": "Fill in the blanks using a word bank",
  "hw-type-8": "Fill in the blanks with correct verb forms",
  "hw-type-9": "Fill in the blanks with prepositions/articles",
  "hw-type-10": "Complete sentence transformation exercises",
  "hw-type-11": "Match vocabulary words to definitions",
  "hw-type-12": "Match questions with responses",
  "hw-type-13": "Unscramble sentences",
  "hw-type-14": "Rearrange sentences into a paragraph",
  "hw-type-15": "Complete dialogues with missing lines",
  "hw-type-16": "Choose the correct multiple-choice answer",
  "hw-type-17": "Correct grammar mistakes in sentences",
  "hw-type-18": "Rewrite sentences using target grammar",
  "hw-type-19": "Rewrite sentences in another tense",
  "hw-type-20": "Combine two sentences into one",
  "hw-type-21": "Write sentences using target vocabulary",
  "hw-type-22": "Write questions for given answers",
  "hw-type-23": "Complete sentence stems",
  "hw-type-24": "Write a short paragraph on a topic",
  "hw-type-25": "Write an email/message using target expressions",
  "hw-type-26": "Listen and answer comprehension questions",
  "hw-type-27": "Listen and complete missing words",
  "hw-type-28": "Listen and choose the correct answer",
  "hw-type-29": "Listen and sequence events/pictures",
  "hw-type-30": "Listen and take notes",
  "hw-type-31": "Dictation exercises",
  "hw-type-32": "Read aloud and submit a recording",
  "hw-type-33": "Repeat and record pronunciation practice",
  "hw-type-34": "Describe a picture using target vocabulary",
  "hw-type-35": "Compare two pictures/ideas",
  "hw-type-36": "Record answers to speaking questions",
  "hw-type-37": "Give a short spoken summary",
  "hw-type-38": "Roleplay a dialogue and record it",
  "hw-type-39": "Practice minimal pairs pronunciation",
  "hw-type-40": "Categorize vocabulary by topic",
  "hw-type-41": "Choose synonyms/antonyms",
  "hw-type-42": "Identify parts of speech",
  "hw-type-43": "Complete collocations/phrasal verbs",
  "hw-type-44": "Label pictures with vocabulary words",
  "hw-type-45": "Answer open-ended discussion questions",
  "hw-type-46": "Write opinion responses",
  "hw-type-47": "Summarize a short article/video",
  "hw-type-48": "Translate sentences into English",
  "hw-type-49": "Find and correct errors in a paragraph",
  "hw-type-50": "Complete cloze reading passages",
  "hw-type-51": "Identify tone/purpose of a text",
  "hw-type-52": "Write definitions for vocabulary words",
  "hw-type-53": "Create example sentences from prompts",
  "hw-type-54": "Complete charts/tables from reading or listening",
  "hw-type-55": "Answer WH-questions about a text",
  "hw-type-56": "Choose the correct word form",
  "hw-type-57": "Practice pronunciation stress marking",
  "hw-type-58": "Complete conversation gap-fills",
  "hw-type-59": "Put dialogue lines in correct order",
  "hw-type-60": "Write a response to a prompt using target grammar"
}